Workbook

Sheet Cover & Sources
B2: Eli Lilly and Company (NYSE: LLY)
B3: FP&A / 3-Statement Financial Model — Historical Phase (FY2021–FY2025)
B4: Prepared as a self-directed portfolio project
B6: IMPORTANT NOTE ON SEGMENTS
B7: Eli Lilly operates and reports as a single business segment ("human pharmaceutical products"). There is no multi-segment revenue breakdown to report.
B9: PRIMARY SOURCE
B10: Eli Lilly and Company Form 10-K, fiscal year ended Dec 31, 2025.
B11: Filed with SEC on Feb 12, 2026 | SEC EDGAR CIK 0000059478
B12: https://www.sec.gov/Archives/edgar/data/59478/000005947826000013/lly-20251231.htm
B14: AGGREGATED HISTORICAL DATA
B15: Five-year line item detail (income statement, balance sheet, cash flow, product revenue) was compiled via StockAnalysis.com which sources its data from the same SEC 10-K filings.
B16: Income Statement | C16: https://stockanalysis.com/stocks/lly/financials/
B17: Balance Sheet | C17: https://stockanalysis.com/stocks/lly/financials/balance-sheet/
B18: Cash Flow Statement | C18: https://stockanalysis.com/stocks/lly/financials/cash-flow-statement/
B19: Product Revenue (KPIs) | C19: https://stockanalysis.com/stocks/lly/financials/

Sheet Income Statement
B2: Eli Lilly and Company - Consolidated Income Statement
B3: $ in millions, except per-share data | FY ends Dec 31 | Source: SEC 10-K filings (see Cover & Sources)
B5: Item | C5: FY2021 | D5: FY2022 | E5: FY2023 | F5: FY2024 | G5: FY2025
B7: Total Revenue | C7: 28318 | D7: 28541 | E7: 34124 | F7: 45043 | G7: 65179
B8: Revenue Growth % | C8: n/a | D8: =D7/C7-1 -> 0.0078748499 | E8: =E7/D7-1 -> 0.19561333 | F8: =F7/E7-1 -> 0.31998007 | G8: =G7/F7-1 -> 0.4470395
B9: Cost of Sales (COGS) | C9: =C7-C10 -> 7312 | D9: =D7-D10 -> 6629 | E9: =E7-E10 -> 7082 | F9: =F7-F10 -> 8418 | G9: =G7-G10 -> 11052
B10: Gross Profit | C10: 21006 | D10: 21912 | E10: 27042 | F10: 36625 | G10: 54127
B11: Gross Margin % | C11: =C10/C7 -> 0.74178967 | D11: =D10/D7 -> 0.76773764 | E11: =E10/E7 -> 0.79246278 | F11: =F10/F7 -> 0.81311192 | G11: =G10/G7 -> 0.83043618
B13: R&D + SG&A (combined OpEx) | C13: =C10-C14 -> 14649 | D13: =D10-D14 -> 14785 | E13: =E10-E14 -> 20585 | F13: =F10-F14 -> 23726 | G13: =G10-G14 -> 27825
B14: Operating Income | C14: 6357 | D14: 7127 | E14: 6457 | F14: 12899 | G14: 26302
B15: Operating Margin % | C15: =C14/C7 -> 0.22448619 | D15: =D14/D7 -> 0.24971094 | E15: =E14/E7 -> 0.18922166 | F15: =F14/F7 -> 0.2863708 | G15: =G14/G7 -> 0.40353488
B17: Net Income | C17: 5582 | D17: 6245 | E17: 5240 | F17: 10590 | G17: 20640
B18: Net Margin % | C18: =C17/C7 -> 0.19711844 | D18: =D17/D7 -> 0.21880803 | E18: =E17/E7 -> 0.15355761 | F18: =F17/F7 -> 0.23510867 | G18: =G17/G7 -> 0.31666641
B20: Diluted EPS | C20: 6.12 | D20: 6.9 | E20: 5.8 | F20: 11.71 | G20: 22.95
B21: Implied Diluted Shares (M) | C21: =C17/C20 -> 912.0915 | D21: =D17/D20 -> 905.07246 | E21: =E17/E20 -> 903.44828 | F21: =F17/F20 -> 904.35525 | G21: =G17/G20 -> 899.34641
B23: Note: R&D and SG&A are disclosed separately in the 10-K income statement (shown combined here as one derived OpEx line.)

Sheet Balance Sheet
B2: Eli Lilly and Company - Consolidated Balance Sheet
B3: $ in millions | As of Dec 31 | Source: SEC 10-K filings (see Cover & Sources)
B5: Item | C5: FY2021 | D5: FY2022 | E5: FY2023 | F5: FY2024 | G5: FY2025
B7: ASSETS
B8: Cash & Short-Term Investments | C8: 3909 | D8: 2212 | E8: 2928 | F8: 3268 | G8: 7268
B9: Accounts & Trade Receivables | C9: 8127 | D9: 8559 | E9: 11336 | F9: 13276 | G9: 20155
B10: Inventory | C10: 3886 | D10: 4310 | E10: 5773 | F10: 7589 | G10: 13744
B11: Other Current Assets | C11: 2531 | D11: 2954 | E11: 5690 | F11: 8607 | G11: 14462
B12: TOTAL CURRENT ASSETS | C12: =C8+C9+C10+C11 -> 18453 | D12: =D8+D9+D10+D11 -> 18035 | E12: =E8+E9+E10+E11 -> 25727 | F12: =F8+F9+F10+F11 -> 32740 | G12: =G8+G9+G10+G11 -> 55629
B13: Net PP&E | C13: 8985 | D13: 10144 | E13: 12914 | F13: 17102 | G13: 24675
B14: Goodwill | C14: 3892 | D14: 4073 | E14: 4940 | F14: 5770 | G14: 5898
B15: Other Intangible Assets | C15: 7692 | D15: 7207 | E15: 6907 | F15: 6166 | G15: 6521
B16: Long-Term Investments | C16: 3213 | D16: 2902 | E16: 3052 | F16: 3216 | G16: 2802
B17: Other Long-Term Assets | C17: 6572 | D17: 7130 | E17: 10467 | F17: 13721 | G17: 16951
B18: TOTAL ASSETS | C18: =C12+C13+C14+C15+C16+C17 -> 48807 | D18: =D12+D13+D14+D15+D16+D17 -> 49491 | E18: =E12+E13+E14+E15+E16+E17 -> 64007 | F18: =F12+F13+F14+F15+F16+F17 -> 78715 | G18: =G12+G13+G14+G15+G16+G17 -> 112476
B19: LIABILITIES
B20: Accounts Payable | C20: 1671 | D20: 1931 | E20: 2599 | F20: 3229 | G20: 5379
B21: Accrued Expenses | C21: 958.1 | D21: 1060 | E21: 1650 | F21: 2094 | G21: 2375
B22: Short-Term Debt | C22: 1538 | D22: 1501 | E22: 6905 | F22: 5117 | G22: 1635
B23: Other Current Liabilities | C23: 10886 | D23: 12647 | E23: 16140 | F23: 17936 | G23: 25839
B24: TOTAL CURRENT LIABILITIES | C24: =C20+C21+C22+C23 -> 15053.1 | D24: =D20+D21+D22+D23 -> 17139 | E24: =E20+E21+E22+E23 -> 27294 | F24: =F20+F21+F22+F23 -> 28376 | G24: =G20+G21+G22+G23 -> 35228
B25: Long-Term Debt | C25: 15346 | D25: 14738 | E25: 18321 | F25: 28527 | G25: 40868
B26: Other Long-Term Liabilities | C26: 9252 | D26: 6839 | E26: 7529 | F26: 7540 | G26: 9845
B27: TOTAL LIABILITIES | C27: =C24+C25+C26 -> 39651.1 | D27: =D24+D25+D26 -> 38716 | E27: =E24+E25+E26 -> 53144 | F27: =F24+F25+F26 -> 64443 | G27: =G24+G25+G26 -> 85941
B28: EQUITY
B29: Total Shareholders' Equity | C29: 9155 | D29: 10775 | E29: 10864 | F29: 14272 | G29: 26535
B30: TOTAL LIABILITIES & EQUITY | C30: =C27+C29 -> 48806.1 | D30: =D27+D29 -> 49491 | E30: =E27+E29 -> 64008 | F30: =F27+F29 -> 78715 | G30: =G27+G29 -> 112476
B32: Balance Check (Assets - Liab&Equity) | C32: =C18-C30 -> 0.9 | D32: =D18-D30 -> 0 | E32: =E18-E30 -> -1 | F32: =F18-F30 -> 0 | G32: =G18-G30 -> 0

Sheet Cash Flow
B2: Eli Lilly and Company - Consolidated Cash Flow Statement
B3: $ in millions | FY ends Dec 31 | Source: SEC 10-K filings (see Cover & Sources)
B5: Item | C5: FY2021 | D5: FY2022 | E5: FY2023 | F5: FY2024 | G5: FY2025
B7: OPERATING ACTIVITIES
B8: Net Income | C8: 5582 | D8: 6245 | E8: 5240 | F8: 10590 | G8: 20640
B9: Depreciation & Amortization | C9: 1548 | D9: 1523 | E9: 1527 | F9: 1767 | G9: 1997
B10: Stock-Based Compensation | C10: 342.8 | D10: 371.1 | E10: 629 | F10: 646 | G10: 626
B11: Other Adjustments | C11: 179 | D11: -1013 | E11: -420 | F11: 373 | G11: 1023
B12: Change in Receivables | C12: -1278 | D12: -299.6 | E12: -2451 | F12: -2155 | G12: -7000
B13: Change in Inventories | C13: -235.9 | D13: -599.7 | E13: -1425 | F13: -2507 | G13: -4671
B14: Change in Accounts Payable | C14: -1014 | D14: 1692 | E14: 4274 | F14: 2609 | G14: 10187
B15: Change in Other Operating Items | C15: 2243 | D15: -332.2 | E15: -3134 | F15: -2505 | G15: -5989
B16: OPERATING CASH FLOW | C16: =C8+C9+C10+C11+C12+C13+C14+C15 -> 7366.9 | D16: =D8+D9+D10+D11+D12+D13+D14+D15 -> 7586.6 | E16: =E8+E9+E10+E11+E12+E13+E14+E15 -> 4240 | F16: =F8+F9+F10+F11+F12+F13+F14+F15 -> 8818 | G16: =G8+G9+G10+G11+G12+G13+G14+G15 -> 16813
B17: INVESTING ACTIVITIES
B18: Capital Expenditures | C18: -1310 | D18: -1854 | E18: -3448 | F18: -5058 | G18: -7841
B19: Purchases of Intangible Assets | C19: -668.6 | D19: -1131 | E19: -3944 | F19: -3346 | G19: -3008
B20: Proceeds from Sale of Intangibles | C20: 216 | D20: 95.8 | E20: 1604 | F20: 601 | G20: 218
B21: Net Purchases/Sales of Investments | C21: -165.6 | D21: -244 | E21: -223 | F21: -303 | G21: 319
B22: Cash Acquisitions | C22: -747.4 | D22: -327.2 | E22: -1044 | F22: -948 | G22: -661
B23: Other Investing Activities | C23: -191.7 | D23: -302.2 | E23: -98 | F23: -248 | G23: 1
B24: INVESTING CASH FLOW | C24: =C18+C19+C20+C21+C22+C23 -> -2867.3 | D24: =D18+D19+D20+D21+D22+D23 -> -3762.6 | E24: =E18+E19+E20+E21+E22+E23 -> -7153 | F24: =F18+F19+F20+F21+F22+F23 -> -9302 | G24: =G18+G19+G20+G21+G22+G23 -> -10972
B25: FINANCING ACTIVITIES
B26: Net Short-Term Debt Issued (Repaid) | C26: -4 | D26: 1498 | E26: 4691 | F26: -1852 | G26: -4338
B27: Net Long-Term Debt Issued (Repaid) | C27: 505.4 | D27: -1560 | E27: 3959 | F27: 10753 | G27: 12389
B28: Repurchase of Common Stock | C28: -1250 | D28: -1500 | E28: -750 | F28: -2500 | G28: -4108
B29: Common Dividends Paid | C29: -3087 | D29: -3536 | E29: -4069 | F29: -4680 | G29: -5384
B30: Other Financing Activities | C30: -295.9 | D30: -308.9 | E30: -335 | F30: -491 | G30: -772
B31: FINANCING CASH FLOW | C31: =C26+C27+C28+C29+C30+C32 -> -4337.2 | D31: =D26+D27+D28+D29+D30+D32 -> -5574.5 | E31: =E26+E27+E28+E29+E30+E32 -> 3665 | F31: =F26+F27+F28+F29+F30+F32 -> 933 | G31: =G26+G27+G28+G29+G30+G32 -> -1841
B32: FX & Other | C32: -205.7 | D32: -167.6 | E32: 169 | F32: -297 | G32: 372
B33: NET CHANGE IN CASH | C33: =C16+C24+C31+C32 -> -43.3 | D33: =D16+D24+D31+D32 -> -1918.1 | E33: =E16+E24+E31+E32 -> 921 | F33: =F16+F24+F31+F32 -> 152 | G33: =G16+G24+G31+G32 -> 4372
B35: Capital Expenditures (memo) | C35: -1310 | D35: -1854 | E35: -3448 | F35: -5058 | G35: -7841
B36: Free Cash Flow (OCF - CapEx) | C36: =C16+C35 -> 6056.9 | D36: =D16+D35 -> 5732.6 | E36: =E16+E35 -> 792 | F36: =F16+F35 -> 3760 | G36: =G16+G35 -> 8972

Sheet Working Capital & KPIs
B2: Eli Lilly and Company - Working Capital & KPI Analysis
B3: Derived from Income Statement & Balance Sheet tabs (green = cross-sheet link)
B5: Metric | C5: FY2021 | D5: FY2022 | E5: FY2023 | F5: FY2024 | G5: FY2025
B7: Working Capital Efficiency
B8: Days Sales Outstanding (DSO) | C8: ='Balance Sheet'!C9/'Income Statement'!C7*365 -> 104.75157 | D8: ='Balance Sheet'!D9/'Income Statement'!D7*365 -> 109.4578 | E8: ='Balance Sheet'!E9/'Income Statement'!E7*365 -> 121.25308 | F8: ='Balance Sheet'!F9/'Income Statement'!F7*365 -> 107.58031 | G8: ='Balance Sheet'!G9/'Income Statement'!G7*365 -> 112.86726
B9: Days Inventory Outstanding (DIO) | C9: ='Balance Sheet'!C10/'Income Statement'!C9*365 -> 193.98113 | D9: ='Balance Sheet'!D10/'Income Statement'!D9*365 -> 237.31332 | E9: ='Balance Sheet'!E10/'Income Statement'!E9*365 -> 297.5353 | F9: ='Balance Sheet'!F10/'Income Statement'!F9*365 -> 329.055 | G9: ='Balance Sheet'!G10/'Income Statement'!G9*365 -> 453.90518
B10: Days Payable Outstanding (DPO) | C10: ='Balance Sheet'!C20/'Income Statement'!C9*365 -> 83.412883 | D10: ='Balance Sheet'!D20/'Income Statement'!D9*365 -> 106.32297 | E10: ='Balance Sheet'!E20/'Income Statement'!E9*365 -> 133.95016 | F10: ='Balance Sheet'!F20/'Income Statement'!F9*365 -> 140.00772 | G10: ='Balance Sheet'!G20/'Income Statement'!G9*365 -> 177.64522
B11: Cash Conversion Cycle (DSO+DIO-DPO) | C11: =C8+C9-C10 -> 215.31982 | D11: =D8+D9-D10 -> 240.44814 | E11: =E8+E9-E10 -> 284.83822 | F11: =F8+F9-F10 -> 296.62759 | G11: =G8+G9-G10 -> 389.12721
B13: Net Working Capital ($M) | C13: ='Balance Sheet'!C12-'Balance Sheet'!C24 -> 3399.9 | D13: ='Balance Sheet'!D12-'Balance Sheet'!D24 -> 896 | E13: ='Balance Sheet'!E12-'Balance Sheet'!E24 -> -1567 | F13: ='Balance Sheet'!F12-'Balance Sheet'!F24 -> 4364 | G13: ='Balance Sheet'!G12-'Balance Sheet'!G24 -> 20401
B15: Margin & Return Metrics
B16: Gross Margin % | C16: ='Income Statement'!C10/'Income Statement'!C7 -> 0.74178967 | D16: ='Income Statement'!D10/'Income Statement'!D7 -> 0.76773764 | E16: ='Income Statement'!E10/'Income Statement'!E7 -> 0.79246278 | F16: ='Income Statement'!F10/'Income Statement'!F7 -> 0.81311192 | G16: ='Income Statement'!G10/'Income Statement'!G7 -> 0.83043618
B17: Operating Margin % | C17: ='Income Statement'!C14/'Income Statement'!C7 -> 0.22448619 | D17: ='Income Statement'!D14/'Income Statement'!D7 -> 0.24971094 | E17: ='Income Statement'!E14/'Income Statement'!E7 -> 0.18922166 | F17: ='Income Statement'!F14/'Income Statement'!F7 -> 0.2863708 | G17: ='Income Statement'!G14/'Income Statement'!G7 -> 0.40353488
B18: Net Margin % | C18: ='Income Statement'!C17/'Income Statement'!C7 -> 0.19711844 | D18: ='Income Statement'!D17/'Income Statement'!D7 -> 0.21880803 | E18: ='Income Statement'!E17/'Income Statement'!E7 -> 0.15355761 | F18: ='Income Statement'!F17/'Income Statement'!F7 -> 0.23510867 | G18: ='Income Statement'!G17/'Income Statement'!G7 -> 0.31666641
B19: Return on Equity (ROE) | C19: ='Income Statement'!C17/'Balance Sheet'!C29 -> 0.60972146 | D19: ='Income Statement'!D17/'Balance Sheet'!D29 -> 0.57958237 | E19: ='Income Statement'!E17/'Balance Sheet'!E29 -> 0.48232695 | F19: ='Income Statement'!F17/'Balance Sheet'!F29 -> 0.74201233 | G19: ='Income Statement'!G17/'Balance Sheet'!G29 -> 0.77784059
B20: Return on Assets (ROA) | C20: ='Income Statement'!C17/'Balance Sheet'!C18 -> 0.11436884 | D20: ='Income Statement'!D17/'Balance Sheet'!D18 -> 0.12618456 | E20: ='Income Statement'!E17/'Balance Sheet'!E18 -> 0.081866046 | F20: ='Income Statement'!F17/'Balance Sheet'!F18 -> 0.13453598 | G20: ='Income Statement'!G17/'Balance Sheet'!G18 -> 0.18350581
B21: Current Ratio | C21: ='Balance Sheet'!C12/'Balance Sheet'!C24 -> 1.2258605 | D21: ='Balance Sheet'!D12/'Balance Sheet'!D24 -> 1.0522784 | E21: ='Balance Sheet'!E12/'Balance Sheet'!E24 -> 0.94258811 | F21: ='Balance Sheet'!F12/'Balance Sheet'!F24 -> 1.1537919 | G21: ='Balance Sheet'!G12/'Balance Sheet'!G24 -> 1.5791132
B22: Debt / Equity | C22: =('Balance Sheet'!C22+'Balance Sheet'!C25)/'Balance Sheet'!C29 -> 1.8442381 | D22: =('Balance Sheet'!D22+'Balance Sheet'!D25)/'Balance Sheet'!D29 -> 1.5070998 | E22: =('Balance Sheet'!E22+'Balance Sheet'!E25)/'Balance Sheet'!E29 -> 2.3219809 | F22: =('Balance Sheet'!F22+'Balance Sheet'!F25)/'Balance Sheet'!F29 -> 2.357343 | G22: =('Balance Sheet'!G22+'Balance Sheet'!G25)/'Balance Sheet'!G29 -> 1.6017712

Sheet Revenue by Product
B2: Eli Lilly and Company - Revenue by Product / Therapeutic Area
B3: $ in millions | Lilly is single-segment
B5: Product | C5: FY2021 | D5: FY2022 | E5: FY2023 | F5: FY2024 | G5: FY2025
B6: Baqsimi (divested 2023) | C6: 113.2 | D6: 139.3 | E6: 677.6 | F6: 29.1 | G6: 0
B7: Mounjaro | C7: 0 | D7: 482.5 | E7: 5163 | F7: 11540 | G7: 22965
B8: Zepbound | C8: 0 | D8: 0 | E8: 175.8 | F8: 4926 | G8: 13542
B9: Trulicity | C9: 6472 | D9: 7440 | E9: 7133 | F9: 5254 | G9: 4276
B10: Jardiance | C10: 1491 | D10: 2066 | E10: 2745 | F10: 3341 | G10: 3432
B11: Humalog | C11: 2453 | D11: 2061 | E11: 1663 | F11: 2325 | G11: 2168
B12: Oncology (Cyramza, Erbitux, Jaypirca, Retevmo, Verzenio, Tyvyt, Inluriyo) | C12: 5741 | D12: 5666 | E12: 6658 | F12: 8752 | G12: 9376
B13: Immunology (Taltz, Olumiant, Omvoh, Ebglyss) | C13: 3361 | D13: 3345 | E13: 3798 | F13: 4393 | G13: 5247
B14: Neuroscience (Emgality, Kisunla) | C14: 1899 | D14: 1546 | E14: 2879 | F14: 1473 | G14: 1391
B15: Humulin | C15: 1223 | D15: 1019 | E15: 852.1 | F15: 917.1 | G15: 705
B16: Basaglar | C16: 892.5 | D16: 760.4 | E16: 728.3 | F16: 676.9 | G16: 626
B17: Trajenta | C17: 372.5 | D17: 383.7 | E17: 386.9 | F17: 353.9 | G17: 318
... B19: Other Product Revenue | C19: 4130 | D19: 3520 | E19: 1122 | F19: 903 | G19: 944
B20: TOTAL REVENUE | C20: =C6+C7+C8+C9+C10+C11+C12+C13+C14+C15+C16+C17+C18+C19 -> 28269.4 | D20: =D6+D7+D8+D9+D10+D11+D12+D13+D14+D15+D16+D17+D18+D19 -> 28509.7 | E20: =E6+E7+E8+E9+E10+E11+E12+E13+E14+E15+E16+E17+E18+E19 -> 34124.8 | F20: =F6+F7+F8+F9+F10+F11+F12+F13+F14+F15+F16+F17+F18+F19 -> 45071.9 | G20: =G6+G7+G8+G9+G10+G11+G12+G13+G14+G15+G16+G17+G18+G19 -> 65179
B21: Income Statement Revenue | C21: =C20-'Income Statement'!C7 -> -48.6 | D21: =D20-'Income Statement'!D7 -> -31.3 | E21: =E20-'Income Statement'!E7 -> 0.8 | F21: =F20-'Income Statement'!F7 -> 28.9 | G21: =G20-'Income Statement'!G7 -> 0
B23: GLP-1 Franchise (Mounjaro + Zepbound) | C23: =C6+C7 -> 113.2 | D23: =D6+D7 -> 621.8 | E23: =E6+E7 -> 5840.6 | F23: =F6+F7 -> 11569.1 | G23: =G6+G7 -> 22965
B24: as % of Total Revenue | C24: =C23/'Income Statement'!C7 -> 0.0039974574 | D24: =D23/'Income Statement'!D7 -> 0.021786202 | E24: =E23/'Income Statement'!E7 -> 0.17115813 | F24: =F23/'Income Statement'!F7 -> 0.25684568 | G24: =G23/'Income Statement'!G7 -> 0.35233741

Sheet Forecast Assumptions
B2: Eli Lilly - 5-Year Forecast Assumptions (FY2026E–FY2030E)
B4: SOURCING NOTE
B5: FY2026E is based on Eli Lilly’s latest company guidance. Management raised its revenue guidance twice during 2026 from $80.0-83.0B in February to $82.0–85.0B following Q1 results and subsequently to $85.0–87.0B following Q2 results on August 5, 2026. This model uses the latest guidance midpoint of $86.0B as the FY2026E revenue estimate. FY2027E–FY2030E represent the model’s base-case assumptions. These estimates are informed by the broader direction of Wall Street expectations including continued double-digit revenue growth that gradually moderates over time but they are not intended to replicate any single consensus forecast. Given inconsistencies across third-party estimates, the projections reflect independent analytical judgment. Accordingly, FY2027E onward should be viewed as the analyst’s own forecast rather than sourced company guidance or consensus estimates.
B6: Items | C6: Assumption | D6: FY2026E | E6: FY2027E | F6: FY2028E | G6: FY2029E | H6: FY2030E
B8: Revenue Growth Drivers
B9: Revenue Growth % | C9: FY2026E reflects Lilly’s latest guidance midpoint of $86B; FY2027E–FY2030E assume gradual growth moderation as the GLP-1 franchise matures and new products contribute. | D9: 0.319 | E9: 0.18 | F9: 0.14 | G9: 0.11 | H9: 0.09
B11: Margin Structure
B12: Gross Margin % | C12: Assumes modest expansion from FY2025A as increased manufacturing scale and operating efficiencies improve product economics. | D12: 0.83 | E12: 0.833 | F12: 0.836 | G12: 0.838 | H12: 0.84
B14: Operating Margin % | C14: Assumes gradual expansion as revenue growth outpaces SG&A and R&D growth creating operating leverage. | D14: 0.42 | E14: 0.43 | F14: 0.44 | G14: 0.45 | H14: 0.46
B16: Net Margin % | C16: Assumes net profitability improves as operating margins expand and earnings grow faster than interest and other fixed costs. | D16: 0.335 | E16: 0.345 | F16: 0.36 | G16: 0.375 | H16: 0.385
B18: Capex, D&A & Working Capital
B20: Capex % of Revenue | C20: Assumes Capex declines as a percentage of revenue as major manufacturing capacity investments are completed. | D20: 0.12 | E20: 0.11 | F20: 0.1 | G20: 0.09 | H20: 0.085
B22: D&A % of Revenue | C22: Assumes D&A increases gradually as newly constructed manufacturing facilities and other assets come online. | D22: 0.033 | E22: 0.036 | F22: 0.039 | G22: 0.041 | H22: 0.043
B24: DSO (days) | C24: Held constant at approximately FY2025A levels, assuming no significant change in Lilly’s collection cycle. | D24: 113 | E24: 113 | F24: 113 | G24: 113 | H24: 113
B26: DIO (days) | C26: Held constant at approximately FY2025A levels, assuming inventory efficiency remains broadly stable. | D26: 98 | E26: 98 | F26: 98 | G26: 98 | H26: 98
B28: DPO (days) | C28: Held constant at approximately FY2025A levels, assuming Lilly’s supplier payment practices remain stable. | D28: 51 | E28: 51 | F28: 51 | G28: 51 | H28: 51
B30: Capital Allocation & Share Count
B32: Dividend Payout Ratio (% of NI) | C32: Assumes a gradual increase in the payout ratio, reflecting continued shareholder returns as earnings and cash generation grow. | D32: 0.26 | E32: 0.27 | F32: 0.28 | G32: 0.29 | H32: 0.3
B34: Annual Share Buybacks ($M) | C34: Held at approximately $4.5B annually, reflecting a moderate and consistent share repurchase program. | D34: 4500 | E34: 4500 | F34: 4500 | G34: 4500 | H34: 4500
B36: Share Count Reduction Rate | C36: Assumes approximately 1% annual reduction in diluted shares outstanding from net share repurchases and dilution. | D36: 0.01 | E36: 0.01 | F36: 0.01 | G36: 0.01 | H36: 0.01

Sheet Forecast Income Statement
B2: Eli Lilly-Forecast Income Statement (FY2026E–FY2030E)
B3: $ in millions | Driven by 'Forecast Assumptions' tab (green) | FY2025A = last actual
B5: Item | C5: FY2026E | D5: FY2027E | E5: FY2028E | F5: FY2029E | G5: FY2030E
B7: Total Revenue | C7: ='Income Statement'!G7*(1+'Forecast Assumptions'!D9) -> 85971.101 | D7: =C7*(1+'Forecast Assumptions'!E9) -> 101445.9 | E7: =D7*(1+'Forecast Assumptions'!F9) -> 115648.33 | F7: =E7*(1+'Forecast Assumptions'!G9) -> 128369.64 | G7: =F7*(1+'Forecast Assumptions'!H9) -> 139922.91
B8: Revenue Growth % | C8: ='Forecast Assumptions'!D9 -> 0.319 | D8: ='Forecast Assumptions'!E9 -> 0.18 | E8: ='Forecast Assumptions'!F9 -> 0.14 | F8: ='Forecast Assumptions'!G9 -> 0.11 | G8: ='Forecast Assumptions'!H9 -> 0.09
B9: Gross Profit | C9: =C7*'Forecast Assumptions'!D12 -> 71356.014 | D9: =D7*'Forecast Assumptions'!E12 -> 84504.434 | E9: =E7*'Forecast Assumptions'!F12 -> 96682 | F9: =F7*'Forecast Assumptions'!G12 -> 107573.76 | G9: =G7*'Forecast Assumptions'!H12 -> 117535.24
B10: Cost of Sales (COGS) | C10: =C7-C9 -> 14615.087 | D10: =D7-D9 -> 16941.465 | E10: =E7-E9 -> 18966.325 | F10: =F7-F9 -> 20795.882 | G10: =G7-G9 -> 22387.665
B11: Gross Margin % | C11: ='Forecast Assumptions'!D12 -> 0.83 | D11: ='Forecast Assumptions'!E12 -> 0.833 | E11: ='Forecast Assumptions'!F12 -> 0.836 | F11: ='Forecast Assumptions'!G12 -> 0.838 | G11: ='Forecast Assumptions'!H12 -> 0.84
B13: Operating Income | C13: =C7*'Forecast Assumptions'!D14 -> 36107.862 | D13: =D7*'Forecast Assumptions'!E14 -> 43621.737 | E13: =E7*'Forecast Assumptions'!F14 -> 50885.263 | F13: =F7*'Forecast Assumptions'!G14 -> 57766.338 | G13: =G7*'Forecast Assumptions'!H14 -> 64364.538
B14: R&D + SG&A (implied combined OpEx) | C14: =C9-C13 -> 35248.151 | D14: =D9-D13 -> 40882.697 | E14: =E9-E13 -> 45796.737 | F14: =F9-F13 -> 49807.421 | G14: =G9-G13 -> 53170.705
B15: Operating Margin % | C15: ='Forecast Assumptions'!D14 -> 0.42 | D15: ='Forecast Assumptions'!E14 -> 0.43 | E15: ='Forecast Assumptions'!F14 -> 0.44 | F15: ='Forecast Assumptions'!G14 -> 0.45 | G15: ='Forecast Assumptions'!H14 -> 0.46
B17: Net Income | C17: =C7*'Forecast Assumptions'!D16 -> 28800.319 | D17: =D7*'Forecast Assumptions'!E16 -> 34998.835 | E17: =E7*'Forecast Assumptions'!F16 -> 41633.397 | F17: =F7*'Forecast Assumptions'!G16 -> 48138.615 | G17: =G7*'Forecast Assumptions'!H16 -> 53870.32
B18: Net Margin % | C18: ='Forecast Assumptions'!D16 -> 0.335 | D18: ='Forecast Assumptions'!E16 -> 0.345 | E18: ='Forecast Assumptions'!F16 -> 0.36 | F18: ='Forecast Assumptions'!G16 -> 0.375 | G18: ='Forecast Assumptions'!H16 -> 0.385
B20: Diluted Shares Outstanding (M) | C20: ='Income Statement'!G21*(1-'Forecast Assumptions'!D36) -> 890.35294 | D20: =C20*(1-'Forecast Assumptions'!E36) -> 881.44941 | E20: =D20*(1-'Forecast Assumptions'!F36) -> 872.63492 | F20: =E20*(1-'Forecast Assumptions'!G36) -> 863.90857 | G20: =F20*(1-'Forecast Assumptions'!H36) -> 855.26948
B21: Diluted EPS | C21: =C17/C20 -> 32.347081 | D21: =D17/D20 -> 39.706006 | E21: =E17/E20 -> 47.709983 | F21: =F17/F20 -> 55.721887 | G21: =G17/G20 -> 62.98637

Sheet Forecast Balance Sheet
B2: Eli Lilly - Forecast Balance Sheet (FY2026E–FY2030E)
B3: $ in millions | Working capital driven by DSO/DIO/DPO | debt held flat | cash rolls forward from Forecast Cash Flow
B5: Known Limitation : Dividends and buybacks are held roughly flat in dollar terms which may cause cash to build faster than it would in reality.
B6: A more advanced model would link payouts to FCF or a target cash balance.
B8: Item | C8: FY2026E | D8: FY2027E | E8: FY2028E | F8: FY2029E | G8: FY2030E
B10: Accounts & Trade Receivables | C10: ='Forecast Income Statement'!C7/365*'Forecast Assumptions'!D24 -> 26615.711 | D10: ='Forecast Income Statement'!D7/365*'Forecast Assumptions'!E24 -> 31406.539 | E10: ='Forecast Income Statement'!E7/365*'Forecast Assumptions'!F24 -> 35803.454 | F10: ='Forecast Income Statement'!F7/365*'Forecast Assumptions'!G24 -> 39741.834 | G10: ='Forecast Income Statement'!G7/365*'Forecast Assumptions'!H24 -> 43318.599
B11: Inventory | C11: ='Forecast Income Statement'!C10/365*'Forecast Assumptions'!D26 -> 3924.0508 | D11: ='Forecast Income Statement'!D10/365*'Forecast Assumptions'!E26 -> 4548.6674 | E11: ='Forecast Income Statement'!E10/365*'Forecast Assumptions'!F26 -> 5092.3284 | F11: ='Forecast Income Statement'!F10/365*'Forecast Assumptions'!G26 -> 5583.5518 | G11: ='Forecast Income Statement'!G10/365*'Forecast Assumptions'!H26 -> 6010.9348
B12: Accounts Payable | C12: ='Forecast Income Statement'!C10/365*'Forecast Assumptions'!D28 -> 2042.1081 | D12: ='Forecast Income Statement'!D10/365*'Forecast Assumptions'!E28 -> 2367.1636 | E12: ='Forecast Income Statement'!E10/365*'Forecast Assumptions'!F28 -> 2650.0893 | F12: ='Forecast Income Statement'!F10/365*'Forecast Assumptions'!G28 -> 2905.726 | G12: ='Forecast Income Statement'!G10/365*'Forecast Assumptions'!H28 -> 3128.1395
B14: Net PP&E (prior + capex - D&A) | C14: ='Balance Sheet'!G13+C15-C16 -> 32154.486 | D14: =C14+D15-D16 -> 39661.482 | E14: =D14+E15-E16 -> 46716.03 | F14: =E14+F15-F16 -> 53006.143 | G14: =F14+G15-G16 -> 58882.905
B15: Capital Expenditures | C15: ='Forecast Income Statement'!C7*'Forecast Assumptions'!D20 -> 10316.532 | D15: ='Forecast Income Statement'!D7*'Forecast Assumptions'!E20 -> 11159.049 | E15: ='Forecast Income Statement'!E7*'Forecast Assumptions'!F20 -> 11564.833 | F15: ='Forecast Income Statement'!F7*'Forecast Assumptions'!G20 -> 11553.268 | G15: ='Forecast Income Statement'!G7*'Forecast Assumptions'!H20 -> 11893.447
B16: Depreciation & Amortization | C16: ='Forecast Income Statement'!C7*'Forecast Assumptions'!D22 -> 2837.0463 | D16: ='Forecast Income Statement'!D7*'Forecast Assumptions'!E22 -> 3652.0524 | E16: ='Forecast Income Statement'!E7*'Forecast Assumptions'!F22 -> 4510.2847 | F16: ='Forecast Income Statement'!F7*'Forecast Assumptions'!G22 -> 5263.1553 | G16: ='Forecast Income Statement'!G7*'Forecast Assumptions'!H22 -> 6016.6851
B18: Total Debt (held flat at FY2025A) | C18: ='Balance Sheet'!G22+'Balance Sheet'!G25 -> 42503 | D18: ='Balance Sheet'!G22+'Balance Sheet'!G25 -> 42503 | E18: ='Balance Sheet'!G22+'Balance Sheet'!G25 -> 42503 | F18: ='Balance Sheet'!G22+'Balance Sheet'!G25 -> 42503 | G18: ='Balance Sheet'!G22+'Balance Sheet'!G25 -> 42503
B20: Shareholders' Equity (roll-forward) | C20: ='Balance Sheet'!G29+'Forecast Cash Flow'!C8+'Forecast Cash Flow'!C20+'Forecast Cash Flow'!C21 -> 43347.236 | D20: =C20+'Forecast Cash Flow'!D8+'Forecast Cash Flow'!D20+'Forecast Cash Flow'!D21 -> 64396.386 | E20: =D20+'Forecast Cash Flow'!E8+'Forecast Cash Flow'!E20+'Forecast Cash Flow'!E21 -> 89872.432 | F20: =E20+'Forecast Cash Flow'!F8+'Forecast Cash Flow'!F20+'Forecast Cash Flow'!F21 -> 119550.85 | G20: =F20+'Forecast Cash Flow'!G8+'Forecast Cash Flow'!G20+'Forecast Cash Flow'!G21 -> 152760.07
B21: Cash & Equivalents (roll-forward) | C21: ='Balance Sheet'!G8+'Forecast Cash Flow'!C24 -> 16623.097 | D21: =C21+'Forecast Cash Flow'!D24 -> 34675.283 | E21: =D21+'Forecast Cash Flow'!E24 -> 56108.196 | F21: =E21+'Forecast Cash Flow'!F24 -> 84025.141 | G21: =F21+'Forecast Cash Flow'!G24 -> 116666.42
B23: Net Working Capital (AR + Inv - AP) | C23: =C10+C11-C12 -> 28497.653 | D23: =D10+D11-D12 -> 33588.042 | E23: =E10+E11-E12 -> 38245.693 | F23: =F10+F11-F12 -> 42419.66 | G23: =G10+G11-G12 -> 46201.394

Sheet Forecast Cash Flow
B2: Eli Lilly - Forecast Cash Flow Statement (FY2026E–FY2030E)
B3: $ in millions | no new debt issuance | no M&A/other investing modeled beyond FY2025A base
B5: Item | C5: FY2026E | D5: FY2027E | E5: FY2028E | F5: FY2029E | G5: FY2030E
B7: OPERATING ACTIVITIES
B8: Net Income | C8: ='Forecast Income Statement'!C17 -> 28800.319 | D8: ='Forecast Income Statement'!D17 -> 34998.835 | E8: ='Forecast Income Statement'!E17 -> 41633.397 | F8: ='Forecast Income Statement'!F17 -> 48138.615 | G8: ='Forecast Income Statement'!G17 -> 53870.32
B9: + Depreciation & Amortization | C9: ='Forecast Balance Sheet'!C16 -> 2837.0463 | D9: ='Forecast Balance Sheet'!D16 -> 3652.0524 | E9: ='Forecast Balance Sheet'!E16 -> 4510.2847 | F9: ='Forecast Balance Sheet'!F16 -> 5263.1553 | G9: ='Forecast Balance Sheet'!G16 -> 6016.6851
B10: (Increase) / Decrease in Receivables | C10: =-('Forecast Balance Sheet'!C10-'Balance Sheet'!G9) -> -6460.7107 | D10: =-('Forecast Balance Sheet'!D10-C8) -> -2606.2198 | E10: =-('Forecast Balance Sheet'!E10-D8) -> -804.61884 | F10: =-('Forecast Balance Sheet'!F10-E8) -> 1891.563 | G10: =-('Forecast Balance Sheet'!G10-F8) -> 4820.0162
B11: (Increase) / Decrease in Inventory | C11: =-('Forecast Balance Sheet'!C11-'Balance Sheet'!G10) -> 9819.9492 | D11: =-('Forecast Balance Sheet'!D11-C9) -> -1711.621 | E11: =-('Forecast Balance Sheet'!E11-D9) -> -1440.2761 | F11: =-('Forecast Balance Sheet'!F11-E9) -> -1073.2672 | G11: =-('Forecast Balance Sheet'!G11-F9) -> -747.77954
B12: Increase / (Decrease) in Payables | C12: ='Forecast Balance Sheet'!C12-'Balance Sheet'!G20 -> -3336.8919 | D12: ='Forecast Balance Sheet'!D12-C10 -> 8827.8743 | E12: ='Forecast Balance Sheet'!E12-D10 -> 5256.3091 | F12: ='Forecast Balance Sheet'!F12-E10 -> 3710.3448 | G12: ='Forecast Balance Sheet'!G12-F10 -> 1236.5765
B13: OPERATING CASH FLOW | C13: =C8+C9+C10+C11+C12 -> 31659.712 | D13: =D8+D9+D10+D11+D12 -> 43160.921 | E13: =E8+E9+E10+E11+E12 -> 49155.096 | F13: =F8+F9+F10+F11+F12 -> 57930.411 | G13: =G8+G9+G10+G11+G12 -> 65195.818
B15: INVESTING ACTIVITIES
B16: Capital Expenditures | C16: =-'Forecast Balance Sheet'!C15 -> -10316.532 | D16: =-'Forecast Balance Sheet'!D15 -> -11159.049 | E16: =-'Forecast Balance Sheet'!E15 -> -11564.833 | F16: =-'Forecast Balance Sheet'!F15 -> -11553.268 | G16: =-'Forecast Balance Sheet'!G15 -> -11893.447
B17: INVESTING CASH FLOW | C17: =C16 -> -10316.532 | D17: =D16 -> -11159.049 | E17: =E16 -> -11564.833 | F17: =F16 -> -11553.268 | G17: =G16 -> -11893.447
B19: FINANCING ACTIVITIES
B20: Dividends Paid | C20: =-C8*'Forecast Assumptions'!D32 -> -7488.0829 | D20: =-D8*'Forecast Assumptions'!E32 -> -9449.6855 | E20: =-E8*'Forecast Assumptions'!F32 -> -11657.351 | F20: =-F8*'Forecast Assumptions'!G32 -> -13960.198 | G20: =-G8*'Forecast Assumptions'!H32 -> -16161.096
B21: Share Buybacks | C21: =-'Forecast Assumptions'!D34 -> -4500 | D21: =-'Forecast Assumptions'!E34 -> -4500 | E21: =-'Forecast Assumptions'!F34 -> -4500 | F21: =-'Forecast Assumptions'!G34 -> -4500 | G21: =-'Forecast Assumptions'!H34 -> -4500
B22: FINANCING CASH FLOW | C22: =C20+C21 -> -11988.083 | D22: =D20+D21 -> -13949.686 | E22: =E20+E21 -> -16157.351 | F22: =F20+F21 -> -18460.198 | G22: =G20+G21 -> -20661.096
B24: NET CHANGE IN CASH | C24: =C13+C17+C22 -> 9355.0967 | D24: =D13+D17+D22 -> 18052.187 | E24: =E13+E17+E22 -> 21432.912 | F24: =F13+F17+F22 -> 27916.945 | G24: =G13+G17+G22 -> 32641.275
B26: Free Cash Flow (OCF - CapEx) | C26: =C13+C16 -> 21343.18 | D26: =D13+D16 -> 32001.872 | E26: =E13+E16 -> 37590.263 | F26: =F13+F16 -> 46377.144 | G26: =G13+G16 -> 53302.371

Sheet Budget vs Actual & Variance
B2: Eli Lilly - FY2026 Budget vs. Actual & Variance Analysis
B3: Uses Lilly's own publicly issued guidance as 'Budget'
B5: Sources: Lilly Q4 2025 earnings release (Feb 4, 2026), Q1 2026 release (Apr 30, 2026), Q2 2026 release (Aug 5, 2026) — investor.lilly.com
B7: Metric | C7: Original Budget (Feb 4, 2026) | D7: Post-Q1 Reforecast (Apr 30, 2026) | E7: Current Guidance (Aug 5, 2026)
B9: Revenue — Low ($B) | C9: 80 | D9: 82 | E9: 85
B10: Revenue — High ($B) | C10: 83 | D10: 85 | E10: 87
B11: Revenue — Midpoint ($B) | C11: =AVERAGE(C9:C10) -> 81.5 | D11: =AVERAGE(D9:D10) -> 83.5 | E11: =AVERAGE(E9:E10) -> 86
B13: Non-GAAP EPS — Low | C13: 33.5 | D13: 35.5 | E13: 35.5
B14: Non-GAAP EPS — High | C14: 35 | D14: 37 | E14: 36.5
B15: Non-GAAP EPS — Midpoint | C15: =AVERAGE(C13:C14) -> 34.25 | D15: =AVERAGE(D13:D14) -> 36.25 | E15: =AVERAGE(E13:E14) -> 36
B17: Variance: Current Guidance vs. Original Budget
B18: Revenue Variance ($B) | C18: =E11-C11 -> 4.5 | F18: Favorable - guidance was raised twice in 2026 due to strong Mounjaro and Zepbound demand and better-than-expected growth from the new oral GLP-1 treatment.
B19: Revenue Variance (%) | C19: =E11/C11-1 -> 0.055214724
B21: EPS Variance ($) | C21: =E15-C15 -> 1.75
B22: EPS Variance (%) | C22: =E15/C15-1 -> 0.051094891
B24: Quarterly Actual Results Delivered vs. Plan
B25: Metric | C25: Q1 2026A | D25: Q2 2026A | E25: H1 2026A (Sum)
B26: Revenue ($B) | C26: 19.8 | D26: 23 | E26: =C26+D26 -> 42.8
B27: Revenue Growth % YoY | C27: 0.56 | D27: 0.48
B28: Reported Diluted EPS | C28: 8.26 | D28: 7.94
B29: Non-GAAP Diluted EPS | C29: 8.55 | D29: 8.38
B31: Implied H2 2026 Revenue Needed (to hit current guidance midpoint) | C31: =E11-E26 -> 43.2
B33: Interpretation: FY2026 is tracking as a “beat-and-raise” year with positive variance driven primarily by strong volume growth and higher demand rather than one-time factors.

Sheet KPI Dashboard
B2: Eli Lilly - Management KPI Dashboard
B3: FY2021A–FY2025A actuals + FY2026E–FY2030E forecast | Data linked from Income Statement / Forecast tabs
B5: Metric | C5: FY21A | D5: FY22A | E5: FY23A | F5: FY24A | G5: FY25A | H5: FY26E | I5: FY27E | J5: FY28E | K5: FY29E | L5: FY30E
B7: Revenue ($M) | C7: ='Income Statement'!C7 -> 28318 | D7: ='Income Statement'!D7 -> 28541 | E7: ='Income Statement'!E7 -> 34124 | F7: ='Income Statement'!F7 -> 45043 | G7: ='Income Statement'!G7 -> 65179 | H7: ='Forecast Income Statement'!C7 -> 85971.101 | I7: ='Forecast Income Statement'!D7 -> 101445.9 | J7: ='Forecast Income Statement'!E7 -> 115648.33 | K7: ='Forecast Income Statement'!F7 -> 128369.64 | L7: ='Forecast Income Statement'!G7 -> 139922.91
B8: Revenue Growth % | C8: ='Income Statement'!C8 -> n/a | D8: ='Income Statement'!D8 -> 0.0078748499 | E8: ='Income Statement'!E8 -> 0.19561333 | F8: ='Income Statement'!F8 -> 0.31998007 | G8: ='Income Statement'!G8 -> 0.4470395 | H8: ='Forecast Income Statement'!C8 -> 0.319 | I8: ='Forecast Income Statement'!D8 -> 0.18 | J8: ='Forecast Income Statement'!E8 -> 0.14 | K8: ='Forecast Income Statement'!F8 -> 0.11 | L8: ='Forecast Income Statement'!G8 -> 0.09
B9: Gross Margin % | C9: ='Income Statement'!C11 -> 0.74178967 | D9: ='Income Statement'!D11 -> 0.76773764 | E9: ='Income Statement'!E11 -> 0.79246278 | F9: ='Income Statement'!F11 -> 0.81311192 | G9: ='Income Statement'!G11 -> 0.83043618 | H9: ='Forecast Income Statement'!C11 -> 0.83 | I9: ='Forecast Income Statement'!D11 -> 0.833 | J9: ='Forecast Income Statement'!E11 -> 0.836 | K9: ='Forecast Income Statement'!F11 -> 0.838 | L9: ='Forecast Income Statement'!G11 -> 0.84
B10: Operating Margin % | C10: ='Income Statement'!C15 -> 0.22448619 | D10: ='Income Statement'!D15 -> 0.24971094 | E10: ='Income Statement'!E15 -> 0.18922166 | F10: ='Income Statement'!F15 -> 0.2863708 | G10: ='Income Statement'!G15 -> 0.40353488 | H10: ='Forecast Income Statement'!C15 -> 0.42 | I10: ='Forecast Income Statement'!D15 -> 0.43 | J10: ='Forecast Income Statement'!E15 -> 0.44 | K10: ='Forecast Income Statement'!F15 -> 0.45 | L10: ='Forecast Income Statement'!G15 -> 0.46
B11: Net Margin % | C11: ='Income Statement'!C18 -> 0.19711844 | D11: ='Income Statement'!D18 -> 0.21880803 | E11: ='Income Statement'!E18 -> 0.15355761 | F11: ='Income Statement'!F18 -> 0.23510867 | G11: ='Income Statement'!G18 -> 0.31666641 | H11: ='Forecast Income Statement'!C18 -> 0.335 | I11: ='Forecast Income Statement'!D18 -> 0.345 | J11: ='Forecast Income Statement'!E18 -> 0.36 | K11: ='Forecast Income Statement'!F18 -> 0.375 | L11: ='Forecast Income Statement'!G18 -> 0.385
B12: Diluted EPS | C12: ='Income Statement'!C20 -> 6.12 | D12: ='Income Statement'!D20 -> 6.9 | E12: ='Income Statement'!E20 -> 5.8 | F12: ='Income Statement'!F20 -> 11.71 | G12: ='Income Statement'!G20 -> 22.95 | H12: ='Forecast Income Statement'!C21 -> 32.347081 | I12: ='Forecast Income Statement'!D21 -> 39.706006 | J12: ='Forecast Income Statement'!E21 -> 47.709983 | K12: ='Forecast Income Statement'!F21 -> 55.721887 | L12: ='Forecast Income Statement'!G21 -> 62.98637
B13: GLP-1 Franchise % of Revenue | C13: 0.004 | D13: 0.022 | E13: 0.171 | F13: 0.257 | G13: 0.352 | H13: 0.6 | I13: 0.63 | J13: 0.65 | K13: 0.67 | L13: 0.68

Sheet Scenario Analysis
B2: Eli Lilly - Bull / Base / Bear Scenario Analysis (FY2030E)
B3: Base case = Forecast Assumptions tab. Bull/Bear rebuild the 5-year compounding path with different assumptions.
B5: Assumption | C5: Bear Case | D5: Base Case | E5: Bull Case
B6: Avg. Annual Revenue Growth FY26-30E | C6: 0.1 | D6: 0.164 | E6: 0.22 | F6: Bear: Intensifying oral GLP-1 competition, especially Novo Nordisk’s Wegovy pill limits Lilly’s share gains. Pricing pressure and continued manufacturing/R&D investment constrain margins. Bull: Successful 2027 retatrutide submission/launch, sustained Mounjaro/Zepbound strength, rapid Foundayo adoption and stronger international expansion accelerate growth.
B7: FY2030E Operating Margin | C7: 0.4 | D7: 0.46 | E7: 0.5 | F7: Bear: Elevated reinvestment in manufacturing, R&D and pricing concessions limits margin expansion. Bull: Operating leverage improves as the fixed R&D/manufacturing base is spread across a larger revenue base.
B8: FY2030E Net Margin | C8: 0.32 | D8: 0.385 | E8: 0.42
B10: Resulting Outputs
B11: FY2030E Revenue ($M) | C11: ='Income Statement'!G7*(1+C6)^5 -> 104971.43 | D11: ='Income Statement'!G7*(1+D6)^5 -> 139274.82 | E11: ='Income Statement'!G7*(1+E6)^5 -> 176159.82
B12: FY2030E Operating Income ($M) | C12: =C11*C7 -> 41988.573 | D12: =D11*D7 -> 64066.416 | E12: =E11*E7 -> 88079.908
B13: FY2030E Net Income ($M) | C13: =C11*C8 -> 33590.858 | D13: =D11*D8 -> 53620.804 | E13: =E11*E8 -> 73987.122
B14: Implied Diluted EPS (855M shares) | C14: =C13/855 -> 39.287553 | D14: =D13/855 -> 62.714391 | E14: =E13/855 -> 86.534646
B16: FY2030E Revenue vs. Base Case | C16: =C11/D11-1 -> -0.24629998 | E16: =E11/D11-1 -> 0.2648361
B18: Note: Simplified top-down scenario analysis flexing revenue CAGR and FY2030 margins, not a full three-statement forecast. For a fully integrated analysis, adjust revenue, margin, tax, working capital, capex, financing, and share-count assumptions in the Forecast Assumptions tab so the three statements and valuation outputs flow through automatically.
