Workbook

Sheet Cover & Sources
B2: Eli Lilly and Company (NYSE: LLY)
B3: Equity Research & Valuation Model
B4: Self-directed portfolio project | Valuation date: Aug 18, 2026
B6: RELATIONSHIP TO PROJECT 1
B7: This valuation model builds on the historical financials and five-year operating forecast developed in the companion FP&A project for the same company. Historical results (FY2021A–FY2025A) and forecast operating assumptions for FY2026E–FY2030E including revenue, EBIT, D&A, CapEx and working capital are carried forward as core inputs. This workbook adds the valuation framework, incorporating WACC, DCF valuation, trading comparables, sensitivity analysis and Bull/Base/Bear investment scenarios.
B9: NEW MARKET DATA SOURCES
B10: LLY share price, shares outstanding, beta, trading multiples | C10: stockanalysis.com/stocks/lly/statistics
B11: LLY 52-week range, analyst consensus target price | C11: investing.com/equities/eli-lilly-and-co
B12: Lilly 3.95% 2049 bond yield-to-maturity (cost of debt proxy) | C12: tradingview.com/symbols/NYSE-LLY
B13: 10-Year US Treasury yield (risk-free rate) | C13: tradingeconomics.com/united-states/government-bond-yield
B14: Novo Nordisk (NVO) valuation multiples | C14: finance.yahoo.com/quote/NVO
B15: Pfizer (PFE) valuation multiples | C15: stockanalysis.com/stocks/pfe/statistics
B16: Merck (MRK) valuation multiples | C16: stockanalysis.com/stocks/mrk/statistics
B17: AbbVie (ABBV) valuation multiples | C17: multiples.vc/public-comps/abbvie-valuation-multiples
B19: IMPORTANT DATA QUALITY NOTES
B20: Merck’s trailing P/E of 102.0x is a significant outlier, likely reflecting the impact of a one-time charge. Accordingly, the 15.1x forward P/E is used in the comparable-company analysis to improve peer comparability.
B21: Merck’s EV/EBITDA of 28.7x is also elevated relative to peers. Rather than excluding the multiple, it is retained in the comps analysis and explicitly flagged as an outlier.
B22: LLY’s reported beta of 0.51 appears unusually low relative to the stock’s historical volatility. The figure is retained as sourced but stress-tested through the DCF sensitivity analysis given its direct impact on the cost of equity and resulting discount rate.
B24: TAB GUIDE
B25: WACC - cost of equity (CAPM), cost of debt, capital structure weights
B26: DCF Valuation - unlevered FCF build, terminal value, implied share price
B27: Trading Comps - LLY vs. Novo Nordisk, Pfizer, Merck, AbbVie
B28: Sensitivity Analysis - WACC/growth and WACC/beta data tables
B29: Valuation Summary - football field, Bull/Base/Bear, BUY/HOLD/SELL

Sheet WACC
B2: Eli Lilly - Weighted Average Cost of Capital
B3: Black = source-linked inputs | Purple = formulas
B5: COST OF EQUITY (CAPM)
B7: Risk-Free Rate (10Y US Treasury) | C7: 0.047
B8: Levered Beta | C8: 0.51
B9: Equity Risk Premium | C9: 0.05
B10: Cost of Equity (Ke) = Rf + β × ERP | C10: =C7+C8*C9 -> 0.0725
B12: COST OF DEBT
B14: Pre-Tax Cost of Debt | C14: 0.0538
B15: Effective Tax Rate | C15: 0.185
B16: After-Tax Cost of Debt = Kd × (1 - tax) | C16: =C14*(1-C15) -> 0.043847
B18: CAPITAL STRUCTURE
B20: Current Share Price | C20: 1180.16
B21: Diluted Shares Outstanding (M) | C21: 891.74
B22: Market Value of Equity ($M) | C22: =C20*C21 -> 1052395.9
B23: Total Debt ($M) | C23: 42503
B24: Total Capital ($M) | C24: =C22+C23 -> 1094898.9
B25: Weight of Equity (E/V) | C25: =C22/C24 -> 0.96118089
B26: Weight of Debt (D/V) | C26: =C23/C24 -> 0.03881911
B28: WACC | C28: =C25*C10+C26*C16 -> 0.071387716
B30: Note: LLY’s low reported beta and limited financial leverage result in a WACC below the 8–10% range commonly observed for large-cap pharmaceutical companies. This assumption is therefore flagged and tested across the DCF sensitivity analysis.

Sheet DCF Valuation
B2: Eli Lilly - Discounted Cash Flow Valuation
B3: $ in millions except per-share | Valuation date treated as start of FY2026E (see simplification note)
B4: Unlevered FCF inputs (EBIT, D&A, capex, NWC change) carried from Project 1's Forecast tabs
B6: Item | C6: FY2026E | D6: FY2027E | E6: FY2028E | F6: FY2029E | G6: FY2030E
B8: EBIT (Operating Income) | C8: 36107.86 | D8: 43621.74 | E8: 50885.26 | F8: 57766.34 | G8: 64364.54
B10: Less: Taxes on EBIT | C10: =-C8*WACC!$C$15 -> -6679.9541 | D10: =-D8*WACC!$C$15 -> -8070.0219 | E10: =-E8*WACC!$C$15 -> -9413.7731 | F10: =-F8*WACC!$C$15 -> -10686.773 | G10: =-G8*WACC!$C$15 -> -11907.44
B11: EBIT after tax | C11: =C8+C10 -> 29427.906 | D11: =D8+D10 -> 35551.718 | E11: =E8+E10 -> 41471.487 | F11: =F8+F10 -> 47079.567 | G11: =G8+G10 -> 52457.1
B13: Add: D&A | C13: 2837.05 | D13: 3652.05 | E13: 4510.28 | F13: 5263.16 | G13: 6016.69
B14: Less: Capital Expenditures | C14: -10316.53 | D14: -11159.05 | E14: -11564.83 | F14: -11553.27 | G14: -11893.45
B15: Add/Less: Change in Net Working Capital | C15: 22.35 | D15: 4510.03 | E15: 3011.41 | F15: 4528.63 | G15: 5308.82
B17: Unlevered Free Cash Flow | C17: =C11+C13+C14+C15 -> 21970.776 | D17: =D11+D13+D14+D15 -> 32554.748 | E17: =E11+E13+E14+E15 -> 37428.347 | F17: =F11+F13+F14+F15 -> 45318.087 | G17: =G11+G13+G14+G15 -> 51889.16
B19: Discount Period (t) | C19: 1 | D19: 2 | E19: 3 | F19: 4 | G19: 5
B20: Discount Factor = 1/(1+WACC)^t | C20: =1/(1+WACC!$C$28)^C19 -> 0.93336892 | D20: =1/(1+WACC!$C$28)^D19 -> 0.87117755 | E20: =1/(1+WACC!$C$28)^E19 -> 0.81313005 | F20: =1/(1+WACC!$C$28)^F19 -> 0.75895032 | G20: =1/(1+WACC!$C$28)^G19 -> 0.70838065
B21: PV of Unlevered FCF | C21: =C17*C20 -> 20506.839 | D21: =D17*D20 -> 28360.966 | E21: =E17*E20 -> 30434.114 | F21: =F17*F20 -> 34394.177 | G21: =G17*G20 -> 36757.277
B24: TERMINAL VALUE (Gordon Growth Method)
B26: Perpetual Growth Rate (g) | C26: 0.03 | D26: (Terminal growth rate aligned with long-term nominal GDP growth and inflation expectations.)
B27: Terminal Value = UFCF(2030) × (1+g) / (WACC-g) | C27: =G17*(1+C26)/(WACC!$C$28-C26) -> 1291345.4
B28: PV of Terminal Value | C28: =C27*G20 -> 914764.06
B31: EV-TO-EQUITY VALUE RECONCILIATION
B33: Sum of PV of Explicit FCF (FY26E-30E) | C33: =SUM(C21:G21) -> 150453.37
B34: + PV of Terminal Value | C34: =C28 -> 914764.06
B35: Enterprise Value | C35: =C33+C34 -> 1065217.4
B36: - Total Debt (FY2025A) | C36: 42503
B37: + Cash & ST Investments (FY2025A) | C37: 7268
B38: Equity Value | C38: =C35-C36+C37 -> 1029982.4
B39: Diluted Shares Outstanding (M) | C39: =WACC!$C$21 -> 891.74
B41: IMPLIED SHARE PRICE (DCF) | C41: =C38/C39 -> 1155.0255
B42: Current Share Price | C42: =WACC!$C$20 -> 1180.16
B43: Implied Upside / (Downside) | C43: =C41/C42-1 -> -0.021297546
B45: Simplification Note: FY2026E is modeled as a full future year without adjusting for the 4.5 months already elapsed. For greater precision, FY2026E could be stub-discounted with a mid-year convention applied thereafter.

Sheet Trading Comps
B2: Eli Lilly - Trading Comparables
B3: Large-cap pharma peer set | P/E and EV/EBITDA, Aug 2026
B4: Sources: stockanalysis.com, Yahoo Finance (see Cover & Sources)
B6: Company | C6: Ticker | D6: P/E (fwd or trailing) | E6: EV/EBITDA | F6: Notes
B7: Eli Lilly | C7: LLY | D7: 32.41 | E7: 31.49 | F7: Forward P/E is presented alongside the trailing P/E of 41.0x.
B8: Novo Nordisk | C8: NVO | D8: 14.3 | E8: 9.5 | F8: Direct GLP-1 competitor
B9: Pfizer | C9: PFE | D9: 18.56 | E9: 7.47 | F9: Forward P/E of 8.55x reflects the impact of one time items.
B10: Merck | C10: MRK | D10: 15.13 | E10: 28.66 | F10: Forward P/E is used, as trailing P/E of 102x is distorted by a one time charge and EV/EBITDA is elevated versus peers.
B11: AbbVie | C11: ABBV | D11: 19 | E11: 16.7
B13: Peer Average (excluding LLY) | D13: =AVERAGE(D8:D11) -> 16.7475 | E13: =AVERAGE(E8:E11) -> 15.5825
B14: Peer Median (excluding LLY) | D14: =MEDIAN(D8:D11) -> 16.845 | E14: =MEDIAN(E8:E11) -> 13.1
B17: LLY PREMIUM TO PEER GROUP
B19: LLY P/E vs. Peer Median | D19: =D7/D14-1 -> 0.92401306
B20: LLY EV/EBITDA vs. Peer Median | E20: =E7/E14-1 -> 1.4038168
B23: IMPLIED VALUATION FROM COMPS (applying peer median multiple to LLY)
B25: FY2026E Net Income ($M) | C25: 28800.32
B26: Implied Equity Value = Peer Median P/E × FY26E NI | C26: =D14*C25 -> 485141.39
B27: Diluted Shares (M) | C27: =WACC!$C$21 -> 891.74
B29: IMPLIED SHARE PRICE (COMPS) | C29: =C26/C27 -> 544.03906
B31: PEG VALUATION CROSS-CHECK
B33: LLY Forward P/E | C33: =D7 -> 32.41
B34: LLY FY26E-27E EPS Growth (from Project 1 forecast) | C34: 0.228 | D34: {(39.71/32.35)-1 from Project 1 Forecast Income Statement}
B35: Implied PEG Ratio (P/E ÷ growth%) | C35: =D7/(C34*100) -> 1.4214912
B37: Interpretation: a PEG near or below 1.5x suggests LLY's premium P/E is largely justified by its growth rate.

Sheet Sensitivity Analysis
B2: Eli Lilly - DCF Sensitivity Analysis
B3: Implied Share Price Sensitivity to WACC, Growth, and Beta Assumptions
B4: Note: Sensitivity values are manually calculated, with each cell representing an independent DCF recomputation rather than a live Excel Data Table.
B6: Table 1: Implied Share Price - WACC (rows) x Perpetual Growth Rate (columns)
B8: WACC \ g | C8: 0.02 | D8: 0.025 | E8: 0.03 | F8: 0.035 | G8: 0.04
B9: 0.055 | C9: =(SUMPRODUCT('DCF Valuation'!$C$17:$G$17,1/(1+0.055)^('DCF Valuation'!$C$19:$G$19))+('DCF Valuation'!$G$17*(1+0.02)/(0.055-0.02))/(1+0.055)^5-'DCF Valuation'!$C$36+'DCF Valuation'!$C$37)/WACC!$C$21 -> 1435.4323 | D9: =(SUMPRODUCT('DCF Valuation'!$C$17:$G$17,1/(1+0.055)^('DCF Valuation'!$C$19:$G$19))+('DCF Valuation'!$G$17*(1+0.025)/(0.055-0.025))/(1+0.055)^5-'DCF Valuation'!$C$36+'DCF Valuation'!$C$37)/WACC!$C$21 -> 1659.1031 | E9: =(SUMPRODUCT('DCF Valuation'!$C$17:$G$17,1/(1+0.055)^('DCF Valuation'!$C$19:$G$19))+('DCF Valuation'!$G$17*(1+0.03)/(0.055-0.03))/(1+0.055)^5-'DCF Valuation'!$C$36+'DCF Valuation'!$C$37)/WACC!$C$21 -> 1972.2422 | F9: =(SUMPRODUCT('DCF Valuation'!$C$17:$G$17,1/(1+0.055)^('DCF Valuation'!$C$19:$G$19))+('DCF Valuation'!$G$17*(1+0.035)/(0.055-0.035))/(1+0.055)^5-'DCF Valuation'!$C$36+'DCF Valuation'!$C$37)/WACC!$C$21 -> 2441.9508 | G9: =(SUMPRODUCT('DCF Valuation'!$C$17:$G$17,1/(1+0.055)^('DCF Valuation'!$C$19:$G$19))+('DCF Valuation'!$G$17*(1+0.04)/(0.055-0.04))/(1+0.055)^5-'DCF Valuation'!$C$36+'DCF Valuation'!$C$37)/WACC!$C$21 -> 3224.7986
B10: 0.0614 | C10: =(SUMPRODUCT('DCF Valuation'!$C$17:$G$17,1/(1+0.0614)^('DCF Valuation'!$C$19:$G$19))+('DCF Valuation'!$G$17*(1+0.02)/(0.0614-0.02))/(1+0.0614)^5-'DCF Valuation'!$C$36+'DCF Valuation'!$C$37)/WACC!$C$21 -> 1198.6931 | D10: =(SUMPRODUCT('DCF Valuation'!$C$17:$G$17,1/(1+0.0614)^('DCF Valuation'!$C$19:$G$19))+('DCF Valuation'!$G$17*(1+0.025)/(0.0614-0.025))/(1+0.0614)^5-'DCF Valuation'!$C$36+'DCF Valuation'!$C$37)/WACC!$C$21 -> 1350.8145 | E10: =(SUMPRODUCT('DCF Valuation'!$C$17:$G$17,1/(1+0.0614)^('DCF Valuation'!$C$19:$G$19))+('DCF Valuation'!$G$17*(1+0.03)/(0.0614-0.03))/(1+0.0614)^5-'DCF Valuation'!$C$36+'DCF Valuation'!$C$37)/WACC!$C$21 -> 1551.3822 | F10: =(SUMPRODUCT('DCF Valuation'!$C$17:$G$17,1/(1+0.0614)^('DCF Valuation'!$C$19:$G$19))+('DCF Valuation'!$G$17*(1+0.035)/(0.0614-0.035))/(1+0.0614)^5-'DCF Valuation'!$C$36+'DCF Valuation'!$C$37)/WACC!$C$21 -> 1827.9225 | G10: =(SUMPRODUCT('DCF Valuation'!$C$17:$G$17,1/(1+0.0614)^('DCF Valuation'!$C$19:$G$19))+('DCF Valuation'!$G$17*(1+0.04)/(0.0614-0.04))/(1+0.0614)^5-'DCF Valuation'!$C$36+'DCF Valuation'!$C$37)/WACC!$C$21 -> 2233.6873
B11: 0.0714 | C11: =(SUMPRODUCT('DCF Valuation'!$C$17:$G$17,1/(1+0.0714)^('DCF Valuation'!$C$19:$G$19))+('DCF Valuation'!$G$17*(1+0.02)/(0.0714-0.02))/(1+0.0714)^5-'DCF Valuation'!$C$36+'DCF Valuation'!$C$37)/WACC!$C$21 -> 947.13201 | D11: =(SUMPRODUCT('DCF Valuation'!$C$17:$G$17,1/(1+0.0714)^('DCF Valuation'!$C$19:$G$19))+('DCF Valuation'!$G$17*(1+0.025)/(0.0714-0.025))/(1+0.0714)^5-'DCF Valuation'!$C$36+'DCF Valuation'!$C$37)/WACC!$C$21 -> 1039.7128 | E11: =(SUMPRODUCT('DCF Valuation'!$C$17:$G$17,1/(1+0.0714)^('DCF Valuation'!$C$19:$G$19))+('DCF Valuation'!$G$17*(1+0.03)/(0.0714-0.03))/(1+0.0714)^5-'DCF Valuation'!$C$36+'DCF Valuation'!$C$37)/WACC!$C$21 -> 1154.656 | F11: =(SUMPRODUCT('DCF Valuation'!$C$17:$G$17,1/(1+0.0714)^('DCF Valuation'!$C$19:$G$19))+('DCF Valuation'!$G$17*(1+0.035)/(0.0714-0.035))/(1+0.0714)^5-'DCF Valuation'!$C$36+'DCF Valuation'!$C$37)/WACC!$C$21 -> 1301.1771 | G11: =(SUMPRODUCT('DCF Valuation'!$C$17:$G$17,1/(1+0.0714)^('DCF Valuation'!$C$19:$G$19))+('DCF Valuation'!$G$17*(1+0.04)/(0.0714-0.04))/(1+0.0714)^5-'DCF Valuation'!$C$36+'DCF Valuation'!$C$37)/WACC!$C$21 -> 1494.3609
B12: 0.0814 | C12: =(SUMPRODUCT('DCF Valuation'!$C$17:$G$17,1/(1+0.0814)^('DCF Valuation'!$C$19:$G$19))+('DCF Valuation'!$G$17*(1+0.02)/(0.0814-0.02))/(1+0.0814)^5-'DCF Valuation'!$C$36+'DCF Valuation'!$C$37)/WACC!$C$21 -> 777.82565 | D12: =(SUMPRODUCT('DCF Valuation'!$C$17:$G$17,1/(1+0.0814)^('DCF Valuation'!$C$19:$G$19))+('DCF Valuation'!$G$17*(1+0.025)/(0.0814-0.025))/(1+0.0814)^5-'DCF Valuation'!$C$36+'DCF Valuation'!$C$37)/WACC!$C$21 -> 839.2606 | E12: =(SUMPRODUCT('DCF Valuation'!$C$17:$G$17,1/(1+0.0814)^('DCF Valuation'!$C$19:$G$19))+('DCF Valuation'!$G$17*(1+0.03)/(0.0814-0.03))/(1+0.0814)^5-'DCF Valuation'!$C$36+'DCF Valuation'!$C$37)/WACC!$C$21 -> 912.64786 | F12: =(SUMPRODUCT('DCF Valuation'!$C$17:$G$17,1/(1+0.0814)^('DCF Valuation'!$C$19:$G$19))+('DCF Valuation'!$G$17*(1+0.035)/(0.0814-0.035))/(1+0.0814)^5-'DCF Valuation'!$C$36+'DCF Valuation'!$C$37)/WACC!$C$21 -> 1001.8514 | G12: =(SUMPRODUCT('DCF Valuation'!$C$17:$G$17,1/(1+0.0814)^('DCF Valuation'!$C$19:$G$19))+('DCF Valuation'!$G$17*(1+0.04)/(0.0814-0.04))/(1+0.0814)^5-'DCF Valuation'!$C$36+'DCF Valuation'!$C$37)/WACC!$C$21 -> 1112.6016
B13: 0.09 | C13: =(SUMPRODUCT('DCF Valuation'!$C$17:$G$17,1/(1+0.09)^('DCF Valuation'!$C$19:$G$19))+('DCF Valuation'!$G$17*(1+0.02)/(0.09-0.02))/(1+0.09)^5-'DCF Valuation'!$C$36+'DCF Valuation'!$C$37)/WACC!$C$21 -> 671.12092 | D13: =(SUMPRODUCT('DCF Valuation'!$C$17:$G$17,1/(1+0.09)^('DCF Valuation'!$C$19:$G$19))+('DCF Valuation'!$G$17*(1+0.025)/(0.09-0.025))/(1+0.09)^5-'DCF Valuation'!$C$36+'DCF Valuation'!$C$37)/WACC!$C$21 -> 716.42017 | E13: =(SUMPRODUCT('DCF Valuation'!$C$17:$G$17,1/(1+0.09)^('DCF Valuation'!$C$19:$G$19))+('DCF Valuation'!$G$17*(1+0.03)/(0.09-0.03))/(1+0.09)^5-'DCF Valuation'!$C$36+'DCF Valuation'!$C$37)/WACC!$C$21 -> 769.2693 | F13: =(SUMPRODUCT('DCF Valuation'!$C$17:$G$17,1/(1+0.09)^('DCF Valuation'!$C$19:$G$19))+('DCF Valuation'!$G$17*(1+0.035)/(0.09-0.035))/(1+0.09)^5-'DCF Valuation'!$C$36+'DCF Valuation'!$C$37)/WACC!$C$21 -> 831.72735 | G13: =(SUMPRODUCT('DCF Valuation'!$C$17:$G$17,1/(1+0.09)^('DCF Valuation'!$C$19:$G$19))+('DCF Valuation'!$G$17*(1+0.04)/(0.09-0.04))/(1+0.09)^5-'DCF Valuation'!$C$36+'DCF Valuation'!$C$37)/WACC!$C$21 -> 906.67702
B14: 0.1 | C14: =(SUMPRODUCT('DCF Valuation'!$C$17:$G$17,1/(1+0.1)^('DCF Valuation'!$C$19:$G$19))+('DCF Valuation'!$G$17*(1+0.02)/(0.1-0.02))/(1+0.1)^5-'DCF Valuation'!$C$36+'DCF Valuation'!$C$37)/WACC!$C$21 -> 576.09724 | D14: =(SUMPRODUCT('DCF Valuation'!$C$17:$G$17,1/(1+0.1)^('DCF Valuation'!$C$19:$G$19))+('DCF Valuation'!$G$17*(1+0.025)/(0.1-0.025))/(1+0.1)^5-'DCF Valuation'!$C$36+'DCF Valuation'!$C$37)/WACC!$C$21 -> 609.21694 | E14: =(SUMPRODUCT('DCF Valuation'!$C$17:$G$17,1/(1+0.1)^('DCF Valuation'!$C$19:$G$19))+('DCF Valuation'!$G$17*(1+0.03)/(0.1-0.03))/(1+0.1)^5-'DCF Valuation'!$C$36+'DCF Valuation'!$C$37)/WACC!$C$21 -> 647.06802 | F14: =(SUMPRODUCT('DCF Valuation'!$C$17:$G$17,1/(1+0.1)^('DCF Valuation'!$C$19:$G$19))+('DCF Valuation'!$G$17*(1+0.035)/(0.1-0.035))/(1+0.1)^5-'DCF Valuation'!$C$36+'DCF Valuation'!$C$37)/WACC!$C$21 -> 690.74235 | G14: =(SUMPRODUCT('DCF Valuation'!$C$17:$G$17,1/(1+0.1)^('DCF Valuation'!$C$19:$G$19))+('DCF Valuation'!$G$17*(1+0.04)/(0.1-0.04))/(1+0.1)^5-'DCF Valuation'!$C$36+'DCF Valuation'!$C$37)/WACC!$C$21 -> 741.69574
B17: Table 2: Implied Share Price - Beta (rows) x Equity Risk Premium (columns)
B19: Beta \ ERP | C19: 0.04 | D19: 0.045 | E19: 0.05 | F19: 0.055 | G19: 0.06
B20: 0.35 | C20: =(SUMPRODUCT('DCF Valuation'!$C$17:$G$17,1/(1+(WACC!$C$25*(WACC!$C$7+0.35*0.04)+WACC!$C$26*WACC!$C$16))^('DCF Valuation'!$C$19:$G$19))+('DCF Valuation'!$G$17*(1+0.03)/((WACC!$C$25*(WACC!$C$7+0.35*0.04)+WACC!$C$26*WACC!$C$16)-0.03))/(1+(WACC!$C$25*(WACC!$C$7+0.35*0.04)+WACC!$C$26*WACC!$C$16))^5-'DCF Valuation'!$C$36+'DCF Valuation'!$C$37)/WACC!$C$21 -> 1609.1297 | D20: =(SUMPRODUCT('DCF Valuation'!$C$17:$G$17,1/(1+(WACC!$C$25*(WACC!$C$7+0.35*0.045)+WACC!$C$26*WACC!$C$16))^('DCF Valuation'!$C$19:$G$19))+('DCF Valuation'!$G$17*(1+0.03)/((WACC!$C$25*(WACC!$C$7+0.35*0.045)+WACC!$C$26*WACC!$C$16)-0.03))/(1+(WACC!$C$25*(WACC!$C$7+0.35*0.045)+WACC!$C$26*WACC!$C$16))^5-'DCF Valuation'!$C$36+'DCF Valuation'!$C$37)/WACC!$C$21 -> 1519.754 | E20: =(SUMPRODUCT('DCF Valuation'!$C$17:$G$17,1/(1+(WACC!$C$25*(WACC!$C$7+0.35*0.05)+WACC!$C$26*WACC!$C$16))^('DCF Valuation'!$C$19:$G$19))+('DCF Valuation'!$G$17*(1+0.03)/((WACC!$C$25*(WACC!$C$7+0.35*0.05)+WACC!$C$26*WACC!$C$16)-0.03))/(1+(WACC!$C$25*(WACC!$C$7+0.35*0.05)+WACC!$C$26*WACC!$C$16))^5-'DCF Valuation'!$C$36+'DCF Valuation'!$C$37)/WACC!$C$21 -> 1439.3165 | F20: =(SUMPRODUCT('DCF Valuation'!$C$17:$G$17,1/(1+(WACC!$C$25*(WACC!$C$7+0.35*0.055)+WACC!$C$26*WACC!$C$16))^('DCF Valuation'!$C$19:$G$19))+('DCF Valuation'!$G$17*(1+0.03)/((WACC!$C$25*(WACC!$C$7+0.35*0.055)+WACC!$C$26*WACC!$C$16)-0.03))/(1+(WACC!$C$25*(WACC!$C$7+0.35*0.055)+WACC!$C$26*WACC!$C$16))^5-'DCF Valuation'!$C$36+'DCF Valuation'!$C$37)/WACC!$C$21 -> 1366.5423 | G20: =(SUMPRODUCT('DCF Valuation'!$C$17:$G$17,1/(1+(WACC!$C$25*(WACC!$C$7+0.35*0.06)+WACC!$C$26*WACC!$C$16))^('DCF Valuation'!$C$19:$G$19))+('DCF Valuation'!$G$17*(1+0.03)/((WACC!$C$25*(WACC!$C$7+0.35*0.06)+WACC!$C$26*WACC!$C$16)-0.03))/(1+(WACC!$C$25*(WACC!$C$7+0.35*0.06)+WACC!$C$26*WACC!$C$16))^5-'DCF Valuation'!$C$36+'DCF Valuation'!$C$37)/WACC!$C$21 -> 1300.3879
B21: 0.45 | C21: =(SUMPRODUCT('DCF Valuation'!$C$17:$G$17,1/(1+(WACC!$C$25*(WACC!$C$7+0.45*0.04)+WACC!$C$26*WACC!$C$16))^('DCF Valuation'!$C$19:$G$19))+('DCF Valuation'!$G$17*(1+0.03)/((WACC!$C$25*(WACC!$C$7+0.45*0.04)+WACC!$C$26*WACC!$C$16)-0.03))/(1+(WACC!$C$25*(WACC!$C$7+0.45*0.04)+WACC!$C$26*WACC!$C$16))^5-'DCF Valuation'!$C$36+'DCF Valuation'!$C$37)/WACC!$C$21 -> 1417.7914 | D21: =(SUMPRODUCT('DCF Valuation'!$C$17:$G$17,1/(1+(WACC!$C$25*(WACC!$C$7+0.45*0.045)+WACC!$C$26*WACC!$C$16))^('DCF Valuation'!$C$19:$G$19))+('DCF Valuation'!$G$17*(1+0.03)/((WACC!$C$25*(WACC!$C$7+0.45*0.045)+WACC!$C$26*WACC!$C$16)-0.03))/(1+(WACC!$C$25*(WACC!$C$7+0.45*0.045)+WACC!$C$26*WACC!$C$16))^5-'DCF Valuation'!$C$36+'DCF Valuation'!$C$37)/WACC!$C$21 -> 1327.9882 | E21: =(SUMPRODUCT('DCF Valuation'!$C$17:$G$17,1/(1+(WACC!$C$25*(WACC!$C$7+0.45*0.05)+WACC!$C$26*WACC!$C$16))^('DCF Valuation'!$C$19:$G$19))+('DCF Valuation'!$G$17*(1+0.03)/((WACC!$C$25*(WACC!$C$7+0.45*0.05)+WACC!$C$26*WACC!$C$16)-0.03))/(1+(WACC!$C$25*(WACC!$C$7+0.45*0.05)+WACC!$C$26*WACC!$C$16))^5-'DCF Valuation'!$C$36+'DCF Valuation'!$C$37)/WACC!$C$21 -> 1248.2953 | F21: =(SUMPRODUCT('DCF Valuation'!$C$17:$G$17,1/(1+(WACC!$C$25*(WACC!$C$7+0.45*0.055)+WACC!$C$26*WACC!$C$16))^('DCF Valuation'!$C$19:$G$19))+('DCF Valuation'!$G$17*(1+0.03)/((WACC!$C$25*(WACC!$C$7+0.45*0.055)+WACC!$C$26*WACC!$C$16)-0.03))/(1+(WACC!$C$25*(WACC!$C$7+0.45*0.055)+WACC!$C$26*WACC!$C$16))^5-'DCF Valuation'!$C$36+'DCF Valuation'!$C$37)/WACC!$C$21 -> 1177.0994 | G21: =(SUMPRODUCT('DCF Valuation'!$C$17:$G$17,1/(1+(WACC!$C$25*(WACC!$C$7+0.45*0.06)+WACC!$C$26*WACC!$C$16))^('DCF Valuation'!$C$19:$G$19))+('DCF Valuation'!$G$17*(1+0.03)/((WACC!$C$25*(WACC!$C$7+0.45*0.06)+WACC!$C$26*WACC!$C$16)-0.03))/(1+(WACC!$C$25*(WACC!$C$7+0.45*0.06)+WACC!$C$26*WACC!$C$16))^5-'DCF Valuation'!$C$36+'DCF Valuation'!$C$37)/WACC!$C$21 -> 1113.1133
B22: 0.51 | C22: =(SUMPRODUCT('DCF Valuation'!$C$17:$G$17,1/(1+(WACC!$C$25*(WACC!$C$7+0.51*0.04)+WACC!$C$26*WACC!$C$16))^('DCF Valuation'!$C$19:$G$19))+('DCF Valuation'!$G$17*(1+0.03)/((WACC!$C$25*(WACC!$C$7+0.51*0.04)+WACC!$C$26*WACC!$C$16)-0.03))/(1+(WACC!$C$25*(WACC!$C$7+0.51*0.04)+WACC!$C$26*WACC!$C$16))^5-'DCF Valuation'!$C$36+'DCF Valuation'!$C$37)/WACC!$C$21 -> 1322.3807 | D22: =(SUMPRODUCT('DCF Valuation'!$C$17:$G$17,1/(1+(WACC!$C$25*(WACC!$C$7+0.51*0.045)+WACC!$C$26*WACC!$C$16))^('DCF Valuation'!$C$19:$G$19))+('DCF Valuation'!$G$17*(1+0.03)/((WACC!$C$25*(WACC!$C$7+0.51*0.045)+WACC!$C$26*WACC!$C$16)-0.03))/(1+(WACC!$C$25*(WACC!$C$7+0.51*0.045)+WACC!$C$26*WACC!$C$16))^5-'DCF Valuation'!$C$36+'DCF Valuation'!$C$37)/WACC!$C$21 -> 1233.4217 | E22: =(SUMPRODUCT('DCF Valuation'!$C$17:$G$17,1/(1+(WACC!$C$25*(WACC!$C$7+0.51*0.05)+WACC!$C$26*WACC!$C$16))^('DCF Valuation'!$C$19:$G$19))+('DCF Valuation'!$G$17*(1+0.03)/((WACC!$C$25*(WACC!$C$7+0.51*0.05)+WACC!$C$26*WACC!$C$16)-0.03))/(1+(WACC!$C$25*(WACC!$C$7+0.51*0.05)+WACC!$C$26*WACC!$C$16))^5-'DCF Valuation'!$C$36+'DCF Valuation'!$C$37)/WACC!$C$21 -> 1155.0255 | F22: =(SUMPRODUCT('DCF Valuation'!$C$17:$G$17,1/(1+(WACC!$C$25*(WACC!$C$7+0.51*0.055)+WACC!$C$26*WACC!$C$16))^('DCF Valuation'!$C$19:$G$19))+('DCF Valuation'!$G$17*(1+0.03)/((WACC!$C$25*(WACC!$C$7+0.51*0.055)+WACC!$C$26*WACC!$C$16)-0.03))/(1+(WACC!$C$25*(WACC!$C$7+0.51*0.055)+WACC!$C$26*WACC!$C$16))^5-'DCF Valuation'!$C$36+'DCF Valuation'!$C$37)/WACC!$C$21 -> 1085.4202 | G22: =(SUMPRODUCT('DCF Valuation'!$C$17:$G$17,1/(1+(WACC!$C$25*(WACC!$C$7+0.51*0.06)+WACC!$C$26*WACC!$C$16))^('DCF Valuation'!$C$19:$G$19))+('DCF Valuation'!$G$17*(1+0.03)/((WACC!$C$25*(WACC!$C$7+0.51*0.06)+WACC!$C$26*WACC!$C$16)-0.03))/(1+(WACC!$C$25*(WACC!$C$7+0.51*0.06)+WACC!$C$26*WACC!$C$16))^5-'DCF Valuation'!$C$36+'DCF Valuation'!$C$37)/WACC!$C$21 -> 1023.209
B23: 0.65 | C23: =(SUMPRODUCT('DCF Valuation'!$C$17:$G$17,1/(1+(WACC!$C$25*(WACC!$C$7+0.65*0.04)+WACC!$C$26*WACC!$C$16))^('DCF Valuation'!$C$19:$G$19))+('DCF Valuation'!$G$17*(1+0.03)/((WACC!$C$25*(WACC!$C$7+0.65*0.04)+WACC!$C$26*WACC!$C$16)-0.03))/(1+(WACC!$C$25*(WACC!$C$7+0.65*0.04)+WACC!$C$26*WACC!$C$16))^5-'DCF Valuation'!$C$36+'DCF Valuation'!$C$37)/WACC!$C$21 -> 1140.7331 | D23: =(SUMPRODUCT('DCF Valuation'!$C$17:$G$17,1/(1+(WACC!$C$25*(WACC!$C$7+0.65*0.045)+WACC!$C$26*WACC!$C$16))^('DCF Valuation'!$C$19:$G$19))+('DCF Valuation'!$G$17*(1+0.03)/((WACC!$C$25*(WACC!$C$7+0.65*0.045)+WACC!$C$26*WACC!$C$16)-0.03))/(1+(WACC!$C$25*(WACC!$C$7+0.65*0.045)+WACC!$C$26*WACC!$C$16))^5-'DCF Valuation'!$C$36+'DCF Valuation'!$C$37)/WACC!$C$21 -> 1055.2971 | E23: =(SUMPRODUCT('DCF Valuation'!$C$17:$G$17,1/(1+(WACC!$C$25*(WACC!$C$7+0.65*0.05)+WACC!$C$26*WACC!$C$16))^('DCF Valuation'!$C$19:$G$19))+('DCF Valuation'!$G$17*(1+0.03)/((WACC!$C$25*(WACC!$C$7+0.65*0.05)+WACC!$C$26*WACC!$C$16)-0.03))/(1+(WACC!$C$25*(WACC!$C$7+0.65*0.05)+WACC!$C$26*WACC!$C$16))^5-'DCF Valuation'!$C$36+'DCF Valuation'!$C$37)/WACC!$C$21 -> 980.99048 | F23: =(SUMPRODUCT('DCF Valuation'!$C$17:$G$17,1/(1+(WACC!$C$25*(WACC!$C$7+0.65*0.055)+WACC!$C$26*WACC!$C$16))^('DCF Valuation'!$C$19:$G$19))+('DCF Valuation'!$G$17*(1+0.03)/((WACC!$C$25*(WACC!$C$7+0.65*0.055)+WACC!$C$26*WACC!$C$16)-0.03))/(1+(WACC!$C$25*(WACC!$C$7+0.65*0.055)+WACC!$C$26*WACC!$C$16))^5-'DCF Valuation'!$C$36+'DCF Valuation'!$C$37)/WACC!$C$21 -> 915.77725 | G23: =(SUMPRODUCT('DCF Valuation'!$C$17:$G$17,1/(1+(WACC!$C$25*(WACC!$C$7+0.65*0.06)+WACC!$C$26*WACC!$C$16))^('DCF Valuation'!$C$19:$G$19))+('DCF Valuation'!$G$17*(1+0.03)/((WACC!$C$25*(WACC!$C$7+0.65*0.06)+WACC!$C$26*WACC!$C$16)-0.03))/(1+(WACC!$C$25*(WACC!$C$7+0.65*0.06)+WACC!$C$26*WACC!$C$16))^5-'DCF Valuation'!$C$36+'DCF Valuation'!$C$37)/WACC!$C$21 -> 858.08937
B24: 0.8 | C24: =(SUMPRODUCT('DCF Valuation'!$C$17:$G$17,1/(1+(WACC!$C$25*(WACC!$C$7+0.8*0.04)+WACC!$C$26*WACC!$C$16))^('DCF Valuation'!$C$19:$G$19))+('DCF Valuation'!$G$17*(1+0.03)/((WACC!$C$25*(WACC!$C$7+0.8*0.04)+WACC!$C$26*WACC!$C$16)-0.03))/(1+(WACC!$C$25*(WACC!$C$7+0.8*0.04)+WACC!$C$26*WACC!$C$16))^5-'DCF Valuation'!$C$36+'DCF Valuation'!$C$37)/WACC!$C$21 -> 991.78559 | D24: =(SUMPRODUCT('DCF Valuation'!$C$17:$G$17,1/(1+(WACC!$C$25*(WACC!$C$7+0.8*0.045)+WACC!$C$26*WACC!$C$16))^('DCF Valuation'!$C$19:$G$19))+('DCF Valuation'!$G$17*(1+0.03)/((WACC!$C$25*(WACC!$C$7+0.8*0.045)+WACC!$C$26*WACC!$C$16)-0.03))/(1+(WACC!$C$25*(WACC!$C$7+0.8*0.045)+WACC!$C$26*WACC!$C$16))^5-'DCF Valuation'!$C$36+'DCF Valuation'!$C$37)/WACC!$C$21 -> 911.09001 | E24: =(SUMPRODUCT('DCF Valuation'!$C$17:$G$17,1/(1+(WACC!$C$25*(WACC!$C$7+0.8*0.05)+WACC!$C$26*WACC!$C$16))^('DCF Valuation'!$C$19:$G$19))+('DCF Valuation'!$G$17*(1+0.03)/((WACC!$C$25*(WACC!$C$7+0.8*0.05)+WACC!$C$26*WACC!$C$16)-0.03))/(1+(WACC!$C$25*(WACC!$C$7+0.8*0.05)+WACC!$C$26*WACC!$C$16))^5-'DCF Valuation'!$C$36+'DCF Valuation'!$C$37)/WACC!$C$21 -> 841.65588 | F24: =(SUMPRODUCT('DCF Valuation'!$C$17:$G$17,1/(1+(WACC!$C$25*(WACC!$C$7+0.8*0.055)+WACC!$C$26*WACC!$C$16))^('DCF Valuation'!$C$19:$G$19))+('DCF Valuation'!$G$17*(1+0.03)/((WACC!$C$25*(WACC!$C$7+0.8*0.055)+WACC!$C$26*WACC!$C$16)-0.03))/(1+(WACC!$C$25*(WACC!$C$7+0.8*0.055)+WACC!$C$26*WACC!$C$16))^5-'DCF Valuation'!$C$36+'DCF Valuation'!$C$37)/WACC!$C$21 -> 781.28719 | G24: =(SUMPRODUCT('DCF Valuation'!$C$17:$G$17,1/(1+(WACC!$C$25*(WACC!$C$7+0.8*0.06)+WACC!$C$26*WACC!$C$16))^('DCF Valuation'!$C$19:$G$19))+('DCF Valuation'!$G$17*(1+0.03)/((WACC!$C$25*(WACC!$C$7+0.8*0.06)+WACC!$C$26*WACC!$C$16)-0.03))/(1+(WACC!$C$25*(WACC!$C$7+0.8*0.06)+WACC!$C$26*WACC!$C$16))^5-'DCF Valuation'!$C$36+'DCF Valuation'!$C$37)/WACC!$C$21 -> 728.32388
B25: 0.95 | C25: =(SUMPRODUCT('DCF Valuation'!$C$17:$G$17,1/(1+(WACC!$C$25*(WACC!$C$7+0.95*0.04)+WACC!$C$26*WACC!$C$16))^('DCF Valuation'!$C$19:$G$19))+('DCF Valuation'!$G$17*(1+0.03)/((WACC!$C$25*(WACC!$C$7+0.95*0.04)+WACC!$C$26*WACC!$C$16)-0.03))/(1+(WACC!$C$25*(WACC!$C$7+0.95*0.04)+WACC!$C$26*WACC!$C$16))^5-'DCF Valuation'!$C$36+'DCF Valuation'!$C$37)/WACC!$C$21 -> 875.11734 | D25: =(SUMPRODUCT('DCF Valuation'!$C$17:$G$17,1/(1+(WACC!$C$25*(WACC!$C$7+0.95*0.045)+WACC!$C$26*WACC!$C$16))^('DCF Valuation'!$C$19:$G$19))+('DCF Valuation'!$G$17*(1+0.03)/((WACC!$C$25*(WACC!$C$7+0.95*0.045)+WACC!$C$26*WACC!$C$16)-0.03))/(1+(WACC!$C$25*(WACC!$C$7+0.95*0.045)+WACC!$C$26*WACC!$C$16))^5-'DCF Valuation'!$C$36+'DCF Valuation'!$C$37)/WACC!$C$21 -> 799.28762 | E25: =(SUMPRODUCT('DCF Valuation'!$C$17:$G$17,1/(1+(WACC!$C$25*(WACC!$C$7+0.95*0.05)+WACC!$C$26*WACC!$C$16))^('DCF Valuation'!$C$19:$G$19))+('DCF Valuation'!$G$17*(1+0.03)/((WACC!$C$25*(WACC!$C$7+0.95*0.05)+WACC!$C$26*WACC!$C$16)-0.03))/(1+(WACC!$C$25*(WACC!$C$7+0.95*0.05)+WACC!$C$26*WACC!$C$16))^5-'DCF Valuation'!$C$36+'DCF Valuation'!$C$37)/WACC!$C$21 -> 734.58603 | F25: =(SUMPRODUCT('DCF Valuation'!$C$17:$G$17,1/(1+(WACC!$C$25*(WACC!$C$7+0.95*0.055)+WACC!$C$26*WACC!$C$16))^('DCF Valuation'!$C$19:$G$19))+('DCF Valuation'!$G$17*(1+0.03)/((WACC!$C$25*(WACC!$C$7+0.95*0.055)+WACC!$C$26*WACC!$C$16)-0.03))/(1+(WACC!$C$25*(WACC!$C$7+0.95*0.055)+WACC!$C$26*WACC!$C$16))^5-'DCF Valuation'!$C$36+'DCF Valuation'!$C$37)/WACC!$C$21 -> 678.7399 | G25: =(SUMPRODUCT('DCF Valuation'!$C$17:$G$17,1/(1+(WACC!$C$25*(WACC!$C$7+0.95*0.06)+WACC!$C$26*WACC!$C$16))^('DCF Valuation'!$C$19:$G$19))+('DCF Valuation'!$G$17*(1+0.03)/((WACC!$C$25*(WACC!$C$7+0.95*0.06)+WACC!$C$26*WACC!$C$16)-0.03))/(1+(WACC!$C$25*(WACC!$C$7+0.95*0.06)+WACC!$C$26*WACC!$C$16))^5-'DCF Valuation'!$C$36+'DCF Valuation'!$C$37)/WACC!$C$21 -> 630.05577
B27: Highlighted cells = base-case assumptions (WACC=7.14%, g=3.0%, beta=0.51, ERP=5.0%)
B28: Key takeaway: The DCF valuation is particularly sensitive to LLY’s beta assumption. Raising beta toward a more conservative 0.65-0.80 peer range increases the cost of equity and meaningfully lowers the implied share price.

Sheet Valuation Summary
B2: Eli Lilly - Valuation Summary & Investment Recommendation
B3: DCF as the primary valuation approach, supported by trading comps as a cross-check
B5: FOOTBALL FIELD INPUTS
B6: Method / Case | C6: Implied Price
B7: DCF - Bear Case (WACC= 8.14%, g= 2.0%) | C7: ='Sensitivity Analysis'!C12 -> 777.82565
B8: DCF - Base Case (WACC= 7.14%, g= 3.0%) | C8: ='Sensitivity Analysis'!E11 -> 1154.656
B9: DCF - Bull Case (WACC= 6.14%, g= 4.0%) | C9: ='Sensitivity Analysis'!G10 -> 2233.6873
B10: Trading Comps (peer median P/E x FY26E EPS) | C10: ='Trading Comps'!C29 -> 544.03906
B11: 52-Week Low | C11: 685.15
B12: 52-Week High | C12: 1249.45
B13: Street Consensus Target (avg. of 20-23 analysts) | C13: 1305
B14: Current Share Price | C14: =WACC!$C$20 -> 1180.16
B16: BLENDED TARGET PRICE
B17: DCF Weight | C17: 0.85 | D17: DCF weighted more heavily to capture LLY’s unique growth trajectory.
B18: Comps Weight | C18: 0.15 | D18: Trading comps underweighted as raw P/E multiples can be misleading in LLY’s case (see note below)
B20: Analyst note: The peer median P/E of 16.8x reflects companies growing revenue at low-single-digit rates, while LLY is growing at 30%+. Applying the peer multiple without a growth adjustment would undervalue LLY. LLY’s 1.4x PEG remains reasonable when its higher growth profile is considered. Trading comps are therefore used only as a low-weight valuation cross-check
B22: BLENDED TARGET PRICE (Base Case) | C22: =C8*C17+C10*C18 -> 1063.0635
B23: Implied Upside / (Downside) vs. Current Price | C23: =C22/C14-1 -> -0.099220884
B26: INVESTMENT RECOMMENDATION
B27: Rating | C27: =IF(C23>0.1,"BUY",IF(C23<-0.1,"SELL","HOLD")) -> HOLD
B29: INVESTMENT THESIS
B30: Bull: LLY’s GLP-1 franchise remains the primary growth engine representing 56% of FY25 revenue and continuing to expand. Foundayo broadens the opportunity into oral treatment, while two FY26 guidance increases signal strong execution and demand.
B31: Bear: LLY trades at a substantial premium to large-cap pharma peers with a 32–41x P/E vs a 15–19x peer median. This valuation already embeds significant future growth. The 0.51 beta may also understate risk from new GLP-1 competition, pricing/access pressures, and manufacturing execution.
B32: Net: Both DCF and trading comps suggest LLY is broadly fairly valued under the base case. Meaningful upside depends primarily on sustained execution and continued premium valuation, making the bull case more compelling than the base case.
